azure_databricks_sdk_python/__init__.py
azure_databricks_sdk_python/api.py
azure_databricks_sdk_python/client.py
azure_databricks_sdk_python/clusters.py
azure_databricks_sdk_python/exceptions.py
azure_databricks_sdk_python/secrets.py
azure_databricks_sdk_python/tokens.py
azure_databricks_sdk_python/types/__init__.py
azure_databricks_sdk_python/types/auth_methods.py
azure_databricks_sdk_python/types/clusters.py
azure_databricks_sdk_python/types/secrets.py
azure_databricks_sdk_python/types/tokens.py
azure_databricks_sdk_python-0.0.2.dist-info/AUTHORS
azure_databricks_sdk_python-0.0.2.dist-info/LICENSE
azure_databricks_sdk_python-0.0.2.dist-info/METADATA
azure_databricks_sdk_python-0.0.2.dist-info/WHEEL
azure_databricks_sdk_python-0.0.2.dist-info/pbr.json
azure_databricks_sdk_python-0.0.2.dist-info/top_level.txt
azure_databricks_sdk_python-0.0.2.dist-info/RECORD
