Metadata-Version: 2.1
Name: azure-databricks-sdk-python
Version: 0.0.2
Summary: A Python SDK for the Azure Databricks REST API 2.0.
Home-page: http://github.com/aminekaabachi/azure-databricks-sdk-python
Author: Amine Kaabachi
Author-email: ping@kaabachi.io
Maintainer: Amine Kaabachi
Maintainer-email: ping@kaabachi.io
License: MIT
Keywords: azure,databricks
Platform: UNKNOWN
Classifier: Development Status :: 3 - Alpha
Classifier: Intended Audience :: Developers
Classifier: Intended Audience :: Information Technology
Classifier: License :: OSI Approved :: MIT License
Classifier: Operating System :: OS Independent
Classifier: Programming Language :: Python
Classifier: Programming Language :: Python :: 3
Classifier: Programming Language :: Python :: 3.6
Requires-Dist: requests (==2.24.0)
Requires-Dist: cattrs
